Classfile /sdcard/Android/data/me.sheimi.sgit/files/repo/munix/jvm/test/Hello.class
  Last modified Jun 17, 2016; size 823 bytes
  MD5 checksum 8dd1540e402b6d57fab541fbc3f578f5
  Compiled from "Hello.java"
public class Hello
  minor version: 0
  major version: 52
  flags: ACC_PUBLIC, ACC_SUPER
Constant pool:
   #1 = Methodref          #15.#32        // java/lang/Object."<init>":()V
   #2 = Fieldref           #33.#34        // java/lang/System.out:Ljava/io/PrintStream;
   #3 = Class              #35            // java/lang/StringBuilder
   #4 = Methodref          #3.#32         // java/lang/StringBuilder."<init>":()V
   #5 = String             #36            // Hello
   #6 = Methodref          #3.#37         // java/lang/StringBuilder.append:(Ljava/lang/String;)Ljava/lang/StringBuilder;
   #7 = Methodref          #3.#38         // java/lang/StringBuilder.toString:()Ljava/lang/String;
   #8 = Methodref          #39.#40        // java/io/PrintStream.println:(Ljava/lang/String;)V
   #9 = Class              #41            // Hello
  #10 = Methodref          #9.#32         // Hello."<init>":()V
  #11 = Fieldref           #9.#42         // Hello.year:I
  #12 = Methodref          #9.#43         // Hello.pow2:(I)I
  #13 = String             #44            // Anass
  #14 = Methodref          #9.#45         // Hello.sayHello:(Ljava/lang/String;)V
  #15 = Class              #46            // java/lang/Object
  #16 = Utf8               name
  #17 = Utf8               Ljava/lang/String;
  #18 = Utf8               year
  #19 = Utf8               I
  #20 = Utf8               <init>
  #21 = Utf8               ()V
  #22 = Utf8               Code
  #23 = Utf8               LineNumberTable
  #24 = Utf8               pow2
  #25 = Utf8               (I)I
  #26 = Utf8               sayHello
  #27 = Utf8               (Ljava/lang/String;)V
  #28 = Utf8               main
  #29 = Utf8               ([Ljava/lang/String;)V
  #30 = Utf8               SourceFile
  #31 = Utf8               Hello.java
  #32 = NameAndType        #20:#21        // "<init>":()V
  #33 = Class              #47            // java/lang/System
  #34 = NameAndType        #48:#49        // out:Ljava/io/PrintStream;
  #35 = Utf8               java/lang/StringBuilder
  #36 = Utf8               Hello
  #37 = NameAndType        #50:#51        // append:(Ljava/lang/String;)Ljava/lang/StringBuilder;
  #38 = NameAndType        #52:#53        // toString:()Ljava/lang/String;
  #39 = Class              #54            // java/io/PrintStream
  #40 = NameAndType        #55:#27        // println:(Ljava/lang/String;)V
  #41 = Utf8               Hello
  #42 = NameAndType        #18:#19        // year:I
  #43 = NameAndType        #24:#25        // pow2:(I)I
  #44 = Utf8               Anass
  #45 = NameAndType        #26:#27        // sayHello:(Ljava/lang/String;)V
  #46 = Utf8               java/lang/Object
  #47 = Utf8               java/lang/System
  #48 = Utf8               out
  #49 = Utf8               Ljava/io/PrintStream;
  #50 = Utf8               append
  #51 = Utf8               (Ljava/lang/String;)Ljava/lang/StringBuilder;
  #52 = Utf8               toString
  #53 = Utf8               ()Ljava/lang/String;
  #54 = Utf8               java/io/PrintStream
  #55 = Utf8               println
{
  java.lang.String name;
    descriptor: Ljava/lang/String;
    flags:

  int year;
    descriptor: I
    flags:

  public Hello();
    descriptor: ()V
    flags: ACC_PUBLIC
    Code:
      stack=1, locals=1, args_size=1
         0: aload_0
         1: invokespecial #1                  // Method java/lang/Object."<init>":()V
         4: return
      LineNumberTable:
        line 2: 0

  int pow2(int);
    descriptor: (I)I
    flags:
    Code:
      stack=2, locals=2, args_size=2
         0: iconst_1
         1: iload_1
         2: ishl
         3: ireturn
      LineNumberTable:
        line 8: 0

  void sayHello(java.lang.String);
    descriptor: (Ljava/lang/String;)V
    flags:
    Code:
      stack=3, locals=2, args_size=2
         0: getstatic     #2                  // Field java/lang/System.out:Ljava/io/PrintStream;
         3: new           #3                  // class java/lang/StringBuilder
         6: dup
         7: invokespecial #4                  // Method java/lang/StringBuilder."<init>":()V
        10: ldc           #5                  // String Hello
        12: invokevirtual #6                  // Method java/lang/StringBuilder.append:(Ljava/lang/String;)Ljava/lang/StringBuilder;
        15: aload_1
        16: invokevirtual #6                  // Method java/lang/StringBuilder.append:(Ljava/lang/String;)Ljava/lang/StringBuilder;
        19: invokevirtual #7                  // Method java/lang/StringBuilder.toString:()Ljava/lang/String;
        22: invokevirtual #8                  // Method java/io/PrintStream.println:(Ljava/lang/String;)V
        25: return
      LineNumberTable:
        line 12: 0
        line 13: 25

  public static void main(java.lang.String[]);
    descriptor: ([Ljava/lang/String;)V
    flags: ACC_PUBLIC, ACC_STATIC
    Code:
      stack=2, locals=3, args_size=1
         0: new           #9                  // class Hello
         3: dup
         4: invokespecial #10                 // Method "<init>":()V
         7: astore_2
         8: aload_2
         9: sipush        2013
        12: putfield      #11                 // Field year:I
        15: aload_2
        16: bipush        7
        18: invokevirtual #12                 // Method pow2:(I)I
        21: istore_1
        22: aload_2
        23: ldc           #13                 // String Anass
        25: invokevirtual #14                 // Method sayHello:(Ljava/lang/String;)V
        28: return
      LineNumberTable:
        line 17: 0
        line 18: 8
        line 19: 15
        line 20: 22
        line 21: 28
}
SourceFile: "Hello.java"
